readable_log_formatter.py
readable_log_formatter-0.1.4.dist-info/DESCRIPTION.rst
readable_log_formatter-0.1.4.dist-info/METADATA
readable_log_formatter-0.1.4.dist-info/RECORD
readable_log_formatter-0.1.4.dist-info/WHEEL
readable_log_formatter-0.1.4.dist-info/metadata.json
readable_log_formatter-0.1.4.dist-info/top_level.txt
